setup.py
basic_GaussBin_distributions/Binomialdistribution.py
basic_GaussBin_distributions/Gaussiandistribution.py
basic_GaussBin_distributions/Generaldistribution.py
basic_GaussBin_distributions/__init__.py
basic_GaussBin_distributions.egg-info/PKG-INFO
basic_GaussBin_distributions.egg-info/SOURCES.txt
basic_GaussBin_distributions.egg-info/dependency_links.txt
basic_GaussBin_distributions.egg-info/not-zip-safe
basic_GaussBin_distributions.egg-info/top_level.txt