Metadata-Version: 1.0
Name: basic-GaussBin-distributions
Version: 0.1
Summary: Gaussian and Binomial distributions for basic operations
Home-page: UNKNOWN
Author: UNKNOWN
Author-email: UNKNOWN
License: UNKNOWN
Platform: UNKNOWN
